{
    "type": "chest",
    "pools": [
      {
        "rolls": {
          "min": 3,
          "max": 8
        },
        "entries": [
          {
            "type": "loot_table",
            "weight": 10,
            "name": "dsd:chest/iron/tool",
            "functions": [
              {
                "function": "set_count",
                "count": 1
              }
            ]
          },
          {
            "type": "loot_table",
            "weight": 1,
            "name": "dsd:chest/diamond/tool",
            "functions": [
              {
                "function": "set_count",
                "count": 1
              }
            ]
          },
          {
            "type": "loot_table",
            "weight": 10,
            "name": "dsd:chest/iron/weapon",
            "functions": [
              {
                "function": "set_count",
                "count": 1
              }
            ]
          },
          {
            "type": "loot_table",
            "weight": 1,
            "name": "dsd:chest/diamond/weapon",
            "functions": [
              {
                "function": "set_count",
                "count": 1
              }
            ]
          },
          {
            "type": "loot_table",
            "weight": 10,
            "name": "dsd:chest/iron/armor",
            "functions": [
              {
                "function": "set_count",
                "count": 1
              }
            ]
          },
          {
            "type": "loot_table",
            "weight": 1,
            "name": "dsd:chest/diamond/armor",
            "functions": [
              {
                "function": "set_count",
                "count": 1
              }
            ]
          },
          {
            "type": "loot_table",
            "weight": 10,
            "name": "dsd:chest/book",
            "functions": [
              {
                "function": "set_count",
                "count": 1
              }
            ]
          },
          {
            "type": "loot_table",
            "weight": 15,
            "name": "dsd:trial_spawner/extra",
            "functions": [
              {
                "function": "set_count",
                "count": 1
              }
            ]
          },
          {
            "type": "loot_table",
            "weight": 15,
            "name": "dsd:trial_spawner/food",
            "functions": [
              {
                "function": "set_count",
                "count": 1
              }
            ]
          },
          {
            "type": "loot_table",
            "weight": 15,
            "name": "dsd:trial_spawner/material",
            "functions": [
              {
                "function": "set_count",
                "count": 1
              }
            ]
          },
          {
            "type": "loot_table",
            "weight": 15,
            "name": "dsd:trial_spawner/suspicious_stew",
            "functions": [
              {
                "function": "set_count",
                "count": 1
              }
            ]
          }
        ]
      }
    ]
  }